Workbook

Sheet Sheet0
A1: ID | B1: CAT | C1: CODE | D1: HEADING | E1: PARENT_ID | F1: PARENT_CODE | G1: LEVEL | H1: DESC
A2: A | B2: =IF(G2>1,VLOOKUP(LEFT(C2,2),Sheet1!$A$2:$B$88,2,FALSE),C2) -> A | C2: A | D2: AGRICULTURE, FORESTRY AND FISHING | G2: 1 | H2: This section includes the exploitation of vegetal and animal natural resources, comprising the activities of growing of crops, raising and breeding of animals, harvesting of timber and other plants, and the production of animal products from a farm or natural habitats. This section also includes organic agriculture, aquaculture, the growing of genetically modified crops and the raising of genetically modified animals. This section excludes undifferentiated subsistence goods-producing activities of households, which are classified in class 98.10.
A3: 01 | B3: =IF(G3>1,VLOOKUP(LEFT(C3,2),Sheet1!$A$2:$B$88,2,FALSE),C3) -> A | C3: 01 | D3: Crop and animal production, hunting and related service activities | E3: A | F3: A | G3: 2 | H3: This division includes two basic activities, namely the production of crop products and the production of animal products. Mixed farming (group 01.5) breaks with the usual principles for identifying the main activity. It accepts that many agricultural units have a reasonably balanced production of crops and animals, and that it would be arbitrary to classify them in one category or the other. This division includes the soilless cultivation of crops, such as using hydroponic and aquaponic methods. This division also includes service activities incidental to agriculture, as well as hunting, trapping and related activities. Agricultural activities exclude any subsequent processing of the agricultural products (classified under divisions 10, 11 and 12), beyond that needed to prepare them for the primary markets. The preparation of products for the primary markets is included here. This division excludes field construction (for example, agricultural land terracing, drainage, preparing rice paddies) classified in section F and buyers and cooperative associations engaged in the marketing of farm products classified in section G. Also excluded are landscape service activities, which are classified in class 81.30.
A4: 011 | B4: =IF(G4>1,VLOOKUP(LEFT(C4,2),Sheet1!$A$2:$B$88,2,FALSE),C4) -> A | C4: 01.1 | D4: Growing of non-perennial crops | E4: 01 | F4: 01 | G4: 3 | H4: This group includes the growing of non-perennial crops, in other words, plants that do not last for more than two growing seasons. Further included is the growing of these plants for the purpose of seed production.
A5: 0111 | B5: =IF(G5>1,VLOOKUP(LEFT(C5,2),Sheet1!$A$2:$B$88,2,FALSE),C5) -> A | C5: 01.11 | D5: Growing of cereals, other than rice, leguminous crops and oil seeds | E5: 011 | F5: 01.1 | G5: 4 | H5: This class includes all forms of growing of cereals, leguminous crops and oil seeds. Further included is the growing of these plants for the purpose of seed production. The growing of these crops is often combined within agricultural units. This class includes: - growing of cereals, e.g.: • wheat • grain maize • sorghum • barley • rye • oats • millet • pseudocereals, in other words, fruits or seeds used as cereals, e.g.: • quinoa • amaranth • chia - growing of leguminous crops, e.g.: • beans • broad beans • chickpeas • cowpeas • lentils • lupines • peas • pigeon peas - growing of oil seeds, e.g.: • soya beans • groundnuts • castor beans • linseed • mustard seed • niger seed • rapeseed • safflower seed • sesame seed • sunflower seed This class excludes: - growing of rice, see 01.12 - growing of sweetcorn, see 01.13 - growing of maize, lupines or kale for fodder, see 01.19 - growing of oleaginous fruits, see 01.26
A6: 0112 | B6: =IF(G6>1,VLOOKUP(LEFT(C6,2),Sheet1!$A$2:$B$88,2,FALSE),C6) -> A | C6: 01.12 | D6: Growing of rice | E6: 011 | F6: 01.1 | G6: 4 | H6: This class includes: - growing of rice
A7: 0113 | B7: =IF(G7>1,VLOOKUP(LEFT(C7,2),Sheet1!$A$2:$B$88,2,FALSE),C7) -> A | C7: 01.13 | D7: Growing of vegetables and melons, roots and tubers | E7: 011 | F7: 01.1 | G7: 4 | H7: This class includes: - growing of leafy or stem vegetables, e.g.: • artichokes • asparagus • cabbages • cauliflower and broccoli • lettuce and chicory • spinach - growing of fruit-bearing vegetables, e.g.: • cucumbers and gherkins • eggplants (aubergines) • tomatoes • watermelons - growing of root, bulb or tuberous vegetables, e.g.: • carrots • turnips • garlic • onions (including shallots) • leeks and other alliaceous vegetables - growing of mushrooms and truffles - growing of vegetable seeds, including sugar beet seeds, excluding other beet seeds - growing of sugar beet - growing of chillies, peppers (Capsicum spp.) - growing of roots and tubers, e.g.: • potatoes • sweet potatoes • cassava • yams • swedes and mangolds This class also includes: - growing of sweetcorn This class excludes: - growing of spices and aromatic, drug and pharmaceutical crops, see 01.28 - growing of mushroom spawn, see 01.30
A8: 0114 | B8: =IF(G8>1,VLOOKUP(LEFT(C8,2),Sheet1!$A$2:$B$88,2,FALSE),C8) -> A | C8: 01.14 | D8: Growing of sugar cane | E8: 011 | F8: 01.1 | G8: 4 | H8: This class excludes: - growing of sugar beet, see 01.13
A9: 0115 | B9: =IF(G9>1,VLOOKUP(LEFT(C9,2),Sheet1!$A$2:$B$88,2,FALSE),C9) -> A | C9: 01.15 | D9: Growing of tobacco | E9: 011 | F9: 01.1 | G9: 4 | H9: This class includes: - growing of unmanufactured tobacco This class also includes: - preliminary processing of tobacco when associated with the growing of tobacco This class excludes: - preparation of tobacco leaves (e.g. sun drying) by a third party, see 01.63 - manufacture of tobacco products, see 12.00
A10: 0116 | B10: =IF(G10>1,VLOOKUP(LEFT(C10,2),Sheet1!$A$2:$B$88,2,FALSE),C10) -> A | C10: 01.16 | D10: Growing of fibre crops | E10: 011 | F10: 01.1 | G10: 4 | H10: This class includes growing of fibre crops, e.g.: - growing of cotton - growing of jute, kenaf and other textile bast fibres - growing of flax and hemp - growing of sisal and other textile fibre of the genus agave - growing of abaca, ramie and other vegetable textile fibres
A11: 0119 | B11: =IF(G11>1,VLOOKUP(LEFT(C11,2),Sheet1!$A$2:$B$88,2,FALSE),C11) -> A | C11: 01.19 | D11: Growing of other non-perennial crops | E11: 011 | F11: 01.1 | G11: 4 | H11: This class includes the growing of all other non-perennial crops, e.g.: - growing of clover, alfalfa, sainfoin, maize, lupines, other grasses, fodder kale and similar forage crops - growing of beet seeds and seeds of forage plants - growing of flowers - cutting of flowers and flower buds - growing of flower seeds This class also includes: - growing of perennial flowers and other ornamental plants This class excludes: - growing of sugar beet seeds, see 01.13 - growing of non-perennial spices and aromatic, drug and pharmaceutical crops, see 01.28
A12: 012 | B12: =IF(G12>1,VLOOKUP(LEFT(C12,2),Sheet1!$A$2:$B$88,2,FALSE),C12) -> A | C12: 01.2 | D12: Growing of perennial crops | E12: 01 | F12: 01 | G12: 3 | H12: This group includes the growing of perennial crops, in other words, plants that last for more than two growing seasons, either dying back after each season or growing continuously. Further included is the growing of these plants for the purpose of seed production. This group excludes: - growing of perennial flowers and other ornamental plants, see 01.19
A13: 0121 | B13: =IF(G13>1,VLOOKUP(LEFT(C13,2),Sheet1!$A$2:$B$88,2,FALSE),C13) -> A | C13: 01.21 | D13: Growing of grapes | E13: 012 | F13: 01.2 | G13: 4 | H13: This class includes: - growing of grapes for consumption or for further production of wine, juice, vinegar and dried fruit (e.g. raisins, zante currants or sultanas) This class excludes: - manufacture of juice, see 10.32 - manufacture of wine, see 11.02
A14: 0122 | B14: =IF(G14>1,VLOOKUP(LEFT(C14,2),Sheet1!$A$2:$B$88,2,FALSE),C14) -> A | C14: 01.22 | D14: Growing of tropical and subtropical fruits | E14: 012 | F14: 01.2 | G14: 4 | H14: This class includes: - growing of tropical and subtropical fruits, e.g.: • avocados • bananas and plantains • dates • figs • mangoes • papayas • pineapples • rambutans • lychees
... A21: 0129 | B21: =IF(G21>1,VLOOKUP(LEFT(C21,2),Sheet1!$A$2:$B$88,2,FALSE),C21) -> A | C21: 01.29 | D21: Growing of other perennial crops | E21: 012 | F21: 01.2 | G21: 4 | H21: This class includes: - growing of rubber trees for harvesting of latex - growing of Christmas trees - growing of trees for extraction of sap - growing of vegetable materials of a kind used primarily for plaiting This class excludes: - growing of flowers, cutting of flower buds and growing of flower seeds, see 01.19 - gathering of tree sap or rubber-like gums in the wild, see 02.30
A22: 013 | B22: =IF(G22>1,VLOOKUP(LEFT(C22,2),Sheet1!$A$2:$B$88,2,FALSE),C22) -> A | C22: 01.3 | D22: Plant propagation | E22: 01 | F22: 01 | G22: 3
A23: 0130 | B23: =IF(G23>1,VLOOKUP(LEFT(C23,2),Sheet1!$A$2:$B$88,2,FALSE),C23) -> A | C23: 01.30 | D23: Plant propagation | E23: 013 | F23: 01.3 | G23: 4 | H23: This class includes the production of all vegetative planting materials, including cuttings, suckers and seedlings either for direct plant propagation or to create plant grafting stock into which a selected scion is grafted for eventual planting to produce crops. This class includes: - growing of plants for planting - growing of plants for ornamental purposes, including turf for transplanting - growing of live plants for bulbs, tubers and roots, cuttings and slips, and mushroom spawn - operation of tree nurseries, except forest tree nurseries This class excludes: - growing of plants for the purpose of seed production, see 01.1, 01.2 - operation of forest tree nurseries, see 02.10
A24: 014 | B24: =IF(G24>1,VLOOKUP(LEFT(C24,2),Sheet1!$A$2:$B$88,2,FALSE),C24) -> A | C24: 01.4 | D24: Animal production | E24: 01 | F24: 01 | G24: 3 | H24: This group includes: - farming (husbandry, raising) and breeding of all animals, except aquatic animals This group excludes: - farm animal boarding and care, see 01.62 - production of hides and skins from slaughterhouses, see 10.11
A25: 0141 | B25: =IF(G25>1,VLOOKUP(LEFT(C25,2),Sheet1!$A$2:$B$88,2,FALSE),C25) -> A | C25: 01.41 | D25: Raising of dairy cattle | E25: 014 | F25: 01.4 | G25: 4 | H25: This class includes: - raising and breeding of dairy cattle and/or buffaloes - production of raw milk from cows or buffaloes - production of bovine semen of dairy breeds This class excludes: - processing of milk, see 10.51
A26: 0142 | B26: =IF(G26>1,VLOOKUP(LEFT(C26,2),Sheet1!$A$2:$B$88,2,FALSE),C26) -> A | C26: 01.42 | D26: Raising of other cattle and buffaloes | E26: 014 | F26: 01.4 | G26: 4 | H26: This class includes: - raising and breeding of cattle and buffaloes for meat - production of bovine semen of meat breeds This class also includes: - raising and breeding of draft cattle or buffaloes - raising and breeding of fighting bulls
A27: 0143 | B27: =IF(G27>1,VLOOKUP(LEFT(C27,2),Sheet1!$A$2:$B$88,2,FALSE),C27) -> A | C27: 01.43 | D27: Raising of horses and other equines | E27: 014 | F27: 01.4 | G27: 4 | H27: This class includes: - raising and breeding of horses, asses, mules or hinnies, regardless of the purpose This class excludes: - operation of racing and riding stables (if they do not have breeding activities), see 93.19
A28: 0144 | B28: =IF(G28>1,VLOOKUP(LEFT(C28,2),Sheet1!$A$2:$B$88,2,FALSE),C28) -> A | C28: 01.44 | D28: Raising of camels and camelids | E28: 014 | F28: 01.4 | G28: 4 | H28: This class includes: - raising and breeding of camels (dromedary) and camelids
A29: 0145 | B29: =IF(G29>1,VLOOKUP(LEFT(C29,2),Sheet1!$A$2:$B$88,2,FALSE),C29) -> A | C29: 01.45 | D29: Raising of sheep and goats | E29: 014 | F29: 01.4 | G29: 4 | H29: This class includes: - raising and breeding of sheep and goats - production of raw sheep or goat milk - production of raw wool This class excludes: - sheep shearing on a fee or contract basis, see 01.62 - production of pulled wool, see 10.11 - processing of milk, see 10.51
A30: 0146 | B30: =IF(G30>1,VLOOKUP(LEFT(C30,2),Sheet1!$A$2:$B$88,2,FALSE),C30) -> A | C30: 01.46 | D30: Raising of swine and pigs | E30: 014 | F30: 01.4 | G30: 4 | H30: This class includes: - raising and breeding of swine and pigs
A31: 0147 | B31: =IF(G31>1,VLOOKUP(LEFT(C31,2),Sheet1!$A$2:$B$88,2,FALSE),C31) -> A | C31: 01.47 | D31: Raising of poultry | E31: 014 | F31: 01.4 | G31: 4 | H31: This class includes: - raising and breeding of poultry, e.g.: • chickens, turkeys, ducks, geese, quails, ostriches or guineafowls - production of eggs from poultry - operation of poultry hatcheries - automated egg hatching for poultry This class excludes: - production of feathers or down, see 10.12
A32: 0148 | B32: =IF(G32>1,VLOOKUP(LEFT(C32,2),Sheet1!$A$2:$B$88,2,FALSE),C32) -> A | C32: 01.48 | D32: Raising of other animals | E32: 014 | F32: 01.4 | G32: 4 | H32: This class includes: - raising and breeding of semi-domesticated or other live animals, e.g.: • birds (except poultry and ostriches) • insects • rabbits and other fur animals • reindeer - production of bird skins from ranching operations or skins from farming reptiles (e.g. snakes and turtles) - raising and breeding of reptiles, except crocodiles - operation of land worm farms, land mollusc farms, land snail farms, etc. - raising of silkworms, production of silkworm cocoons - beekeeping; production of bees’ byproducts (e.g. honey, beeswax, propolis, bee venom or honeycomb); bee propagation for sale - raising and breeding of pets (except fish), e.g.: • cats and dogs • birds (e.g. parakeets) • hamsters This class excludes: - production of hides and skins originating from hunting and trapping, see 01.70 - raising of live ornamental fish, see 03.2 - operation of frog farms, crocodile farms, marine worm farms, see 03.21, 03.22 - operation of fish farms, see 03.21, 03.22 - boarding and training of pets, see 96.99 - operation of shelters for abandoned pets, see 96.99
A33: 015 | B33: =IF(G33>1,VLOOKUP(LEFT(C33,2),Sheet1!$A$2:$B$88,2,FALSE),C33) -> A | C33: 01.5 | D33: Mixed farming | E33: 01 | F33: 01 | G33: 3
A34: 0150 | B34: =IF(G34>1,VLOOKUP(LEFT(C34,2),Sheet1!$A$2:$B$88,2,FALSE),C34) -> A | C34: 01.50 | D34: Mixed farming | E34: 015 | F34: 01.5 | G34: 4 | H34: This class includes: - the combined production of crops and animals without a specialised production of crops or animals This class excludes: - mixed crop farming, see 01.1, 01.2 - mixed animal farming, see 01.4
A35: 016 | B35: =IF(G35>1,VLOOKUP(LEFT(C35,2),Sheet1!$A$2:$B$88,2,FALSE),C35) -> A | C35: 01.6 | D35: Support activities to agriculture and post-harvest crop activities | E35: 01 | F35: 01 | G35: 3 | H35: This group includes activities incidental to agricultural production and activities similar to agriculture not undertaken for production purposes (in the sense of harvesting agricultural products), usually done on a fee or contract basis. Also included are post-harvest crop activities, aimed at preparing agricultural products for the primary market.
A36: 0161 | B36: =IF(G36>1,VLOOKUP(LEFT(C36,2),Sheet1!$A$2:$B$88,2,FALSE),C36) -> A | C36: 01.61 | D36: Support activities for crop production | E36: 016 | F36: 01.6 | G36: 4 | H36: This class includes: - crop production activities on a fee or contract basis: • preparation of fields • establishing a crop • treatment of crops • crop spraying, including by air • trimming of fruit trees and vines • transplanting of rice; thinning of beets • harvesting • pest control (including of rabbits) in connection with agriculture - operation of agricultural irrigation equipment This class also includes: - provision of agricultural machinery with operators and crew - maintenance of own or leased land, keeping it in good condition without agricultural production This class excludes: - post-harvest crop activities, see 01.63 - drainage of agricultural land, see 43.12 - landscape architecture, see 71.11 - activities of agronomists and agricultural economists, see 74.99 - landscape gardening; planting, see 81.30 - organisation of agricultural shows and fairs, see 82.30
A37: 0162 | B37: =IF(G37>1,VLOOKUP(LEFT(C37,2),Sheet1!$A$2:$B$88,2,FALSE),C37) -> A | C37: 01.62 | D37: Support activities for animal production | E37: 016 | F37: 01.6 | G37: 4 | H37: This class includes: - animal production activities on a fee or contract basis: • activities to promote the propagation, growth and output of animals • herd testing services, droving services, agistment services, poultry caponising, coop cleaning, etc. • activities related to artificial insemination • stud services • sheep shearing • farm animal boarding and care This class also includes: - activities of farriers This class excludes: - provision of space for animal boarding only, see 68.20 - agricultural research activities, see 72.10 - veterinary activities, see 75.00 - vaccination of animals, see 75.00 - rental of animals (e.g. herds or racehorses), see 77.39 - pet boarding, see 96.99
A38: 0163 | B38: =IF(G38>1,VLOOKUP(LEFT(C38,2),Sheet1!$A$2:$B$88,2,FALSE),C38) -> A | C38: 01.63 | D38: Post-harvest crop activities and seed processing for propagation | E38: 016 | F38: 01.6 | G38: 4 | H38: This class includes post-harvest crop activities on a fee or contract basis: - preparation of crops for primary markets (e.g. cleaning, trimming, grading or disinfecting) - cotton ginning - preparation of tobacco leaves (e.g. sun drying) - preparation of cocoa beans (e.g. peeling) - waxing of fruit - drying of fruit, vegetables, herbs, spices, medicinal herbs and tobacco - sorting, cleaning and cutting of medicinal herbs - grain drying - post-harvest activities aimed at improving the propagation quality of seed (e.g. by the removal of non-seed materials, or damaged or immature seeds, or by reducing the seed moisture to a safe level for storage) - retting of plants bearing vegetable textile fibres (such as jute, flax or coir), not associated with the growing of vegetable textile fibres - artificial ripening of fruits as a service (e.g. banana ripening) This class also includes: - drying, cleaning, grading and treating of seeds until they are marketed - treatment of genetically modified seeds This class excludes: - preparation of agricultural products by the producer, see the corresponding classes in groups 01.1, 01.2, 01.3 - growing of seeds, see 01.1, 01.2 - processing of seeds to obtain oil, see 10.41 - stemming and redrying of tobacco, see 12.00 - marketing activities of commission merchants and cooperative associations, see division 46 - wholesale of agricultural raw materials, see 46.2 - research to develop or modify new forms of seeds, see 72.10
A39: 017 | B39: =IF(G39>1,VLOOKUP(LEFT(C39,2),Sheet1!$A$2:$B$88,2,FALSE),C39) -> A | C39: 01.7 | D39: Hunting, trapping and related service activities | E39: 01 | F39: 01 | G39: 3
A40: 0170 | B40: =IF(G40>1,VLOOKUP(LEFT(C40,2),Sheet1!$A$2:$B$88,2,FALSE),C40) -> A | C40: 01.70 | D40: Hunting, trapping and related service activities | E40: 017 | F40: 01.7 | G40: 4 | H40: This class includes: - hunting and trapping on a commercial basis - taking of wild animals (dead or alive) for i) food, fur or skin and ii) use in research, in zoos or as pets - production of fur skins and reptile or bird skins from hunting or trapping activities - catching of frogs and collecting of snails in the wild This class also includes: - land-based catching of sea mammals (e.g. walruses or seals) - hunting of foxes, minks and wolves to protect livestock - hunting for animal population control This class excludes: - raising of game animals on ranching operations, see 01.4 - production of bird skins from ranching operations or skins from farming reptiles (e.g. snakes and turtles), see 01.48 - pest control (including rabbits) in connection with agriculture, see 01.61 - whaling, see 03.11 - production of hides and skins originating from slaughterhouses, see 10.11 - hunting for sport or recreation and related service activities, see 93.19 - service activities to promote hunting and trapping, see 94.99
A41: 02 | B41: =IF(G41>1,VLOOKUP(LEFT(C41,2),Sheet1!$A$2:$B$88,2,FALSE),C41) -> A | C41: 02 | D41: Forestry and logging | E41: A | F41: A | G41: 2 | H41: This division includes silviculture and the production of roundwood as well as the extraction and gathering of wild-growing non-wood forest products. Besides the production of timber, forestry activities result in products that undergo little processing, for example, firewood, charcoal or roundwood used in an unprocessed form (such as pit-props or pulpwood). These activities can be carried out in natural, semi-natural or planted forests. Excluded is further processing of wood beginning with sawmilling and planing of wood, see division 16.
A42: 021 | B42: =IF(G42>1,VLOOKUP(LEFT(C42,2),Sheet1!$A$2:$B$88,2,FALSE),C42) -> A | C42: 02.1 | D42: Silviculture and other forestry activities | E42: 02 | F42: 02 | G42: 3
A43: 0210 | B43: =IF(G43>1,VLOOKUP(LEFT(C43,2),Sheet1!$A$2:$B$88,2,FALSE),C43) -> A | C43: 02.10 | D43: Silviculture and other forestry activities | E43: 021 | F43: 02.1 | G43: 4 | H43: This class includes: - growing of standing timber: planting, replanting, transplanting, thinning and conserving of forests, and timber tracts - growing of coppice, pulpwood and firewood - operation of forest tree nurseries - growing of poplar and willow These activities can be carried out in natural, semi-natural or planted forests. This class excludes: - growing of Christmas trees, see 01.29 - operation of tree nurseries, except for forest trees, see 01.30 - gathering of mushrooms and other wild growing non-wood forest products, see 02.30 - production of wood chips and particles, not associated with forestry activities, see 16.11 - production of wood fire logs not associated with forestry activities, see 16.26 - activities relating to amenity tree care and arboriculture, see 81.30 - conservation and maintenance services of national parks, nature parks and reserves, see 91.42
A44: 022 | B44: =IF(G44>1,VLOOKUP(LEFT(C44,2),Sheet1!$A$2:$B$88,2,FALSE),C44) -> A | C44: 02.2 | D44: Logging | E44: 02 | F44: 02 | G44: 3
A45: 0220 | B45: =IF(G45>1,VLOOKUP(LEFT(C45,2),Sheet1!$A$2:$B$88,2,FALSE),C45) -> A | C45: 02.20 | D45: Logging | E45: 022 | F45: 02.2 | G45: 4 | H45: This class includes: - production of roundwood for forest-based manufacturing industries - production of roundwood used in an unprocessed form (e.g. pit-props, fence posts, utility poles) This class also includes: - gathering and production of forest harvesting residues (e.g. brushwood, stumps, wood chips from logging, other forest waste for energy) - production of charcoal in the forest (using traditional methods) This class excludes: - growing of Christmas trees, see 01.29 - growing of standing timber: planting, replanting, transplanting, thinning and conserving of forests, and timber tracts, see 02.10 - gathering of wild growing non-wood forest products, see 02.30 - production of wood chips and particles, not associated with forestry activities, see 16.11 - production of charcoal through distillation of wood, see 20.14
A46: 023 | B46: =IF(G46>1,VLOOKUP(LEFT(C46,2),Sheet1!$A$2:$B$88,2,FALSE),C46) -> A | C46: 02.3 | D46: Gathering of wild growing non-wood products | E46: 02 | F46: 02 | G46: 3
A47: 0230 | B47: =IF(G47>1,VLOOKUP(LEFT(C47,2),Sheet1!$A$2:$B$88,2,FALSE),C47) -> A | C47: 02.30 | D47: Gathering of wild growing non-wood products | E47: 023 | F47: 02.3 | G47: 4 | H47: This class includes: - gathering of wild growing materials, e.g.: • mushrooms, truffles • berries • nuts • balata and other rubber-like gums • cork • lac and resins • balsams • acorns, horse chestnuts • mosses and lichens • vegetable hair / eelgrass This class also includes: - harvesting wild herbs and associated natural drying This class excludes: - non-wild growing of any of these products (except growing of cork trees), see division 01 - growing of mushrooms or truffles, see 01.13 - growing of berries or nuts, see 01.25 - gathering of firewood, see 02.20
A48: 024 | B48: =IF(G48>1,VLOOKUP(LEFT(C48,2),Sheet1!$A$2:$B$88,2,FALSE),C48) -> A | C48: 02.4 | D48: Support services to forestry | E48: 02 | F48: 02 | G48: 3
A49: 0240 | B49: =IF(G49>1,VLOOKUP(LEFT(C49,2),Sheet1!$A$2:$B$88,2,FALSE),C49) -> A | C49: 02.40 | D49: Support services to forestry | E49: 024 | F49: 02.4 | G49: 4 | H49: This class includes carrying out part of the forestry operation on a fee or contract basis. This class includes: - forestry service activities: • forestry inventories • forest management consulting services • timber evaluation • forest fire fighting and prevention • forest pest control - logging service activities: • transport of logs within the forest This class excludes: - operation of forest tree nurseries, see 02.10 - draining of forestry land, see 43.12 - clearing of building sites, see 43.12
A50: 03 | B50: =IF(G50>1,VLOOKUP(LEFT(C50,2),Sheet1!$A$2:$B$88,2,FALSE),C50) -> A | C50: 03 | D50: Fishing and aquaculture | E50: A | F50: A | G50: 2 | H50: This division includes capture fishery and aquaculture, which are characterised by the gathering of marine, brackish or freshwater fish, crustaceans, molluscs, and other organisms and products (for example, aquatic plants, pearls, sponges). The division also includes service activities incidental to marine or freshwater fishery or aquaculture. This division excludes: - processing of fish, crustaceans or molluscs, whether at land-based plants or on factory ships, see 10.20 - building and repairing of ships and boats, see 30.11, 30.13, 33.15, 33.18 - sport or recreational fishing activities, see 93.19
A51: 031 | B51: =IF(G51>1,VLOOKUP(LEFT(C51,2),Sheet1!$A$2:$B$88,2,FALSE),C51) -> A | C51: 03.1 | D51: Fishing | E51: 03 | F51: 03 | G51: 3 | H51: This group includes capture fishery, in other words, the harvesting, collecting and gathering activities directed at removing or collecting live wild aquatic organisms (predominantly fish, molluscs and crustaceans), including plants from the oceanic, coastal or inland waters for human consumption and other purposes by hand or more usually by various types of fishing gear (for example, nets, lines, stationary traps). Such activities can be conducted on the intertidal zones (for example, the collection of molluscs, such as mussels, oysters), coastal waters or offshore waters. These activities also include fishing in restocked water bodies.
A52: 0311 | B52: =IF(G52>1,VLOOKUP(LEFT(C52,2),Sheet1!$A$2:$B$88,2,FALSE),C52) -> A | C52: 03.11 | D52: Marine fishing | E52: 031 | F52: 03.1 | G52: 4 | H52: This class includes: - fishing on a commercial basis in ocean and coastal waters - taking of marine crustaceans and molluscs - whaling - taking of marine aquatic animals (e.g. turtles, sea squirts, tunicates, sea urchins) This class also includes: - gathering of other marine organisms and materials (e.g. natural pearls, sponges, coral, seaweed, algae) This class excludes: - capturing of marine mammals apart from whales (e.g. seals, walruses), see 01.70 - processing of whales on factory ships, see 10.11 - processing of fish, crustaceans and molluscs on factory ships or in factories ashore, see 10.20 - rental of pleasure boats with crew for sea and coastal water transport (e.g. for fishing trips), see 50.10 - fishing inspection, protection and patrol services, see 84.24 - fishing practiced for sport or recreation and related services, see 93.19 - operation of sport fishing preserves, see 93.19
A53: 0312 | B53: =IF(G53>1,VLOOKUP(LEFT(C53,2),Sheet1!$A$2:$B$88,2,FALSE),C53) -> A | C53: 03.12 | D53: Freshwater fishing | E53: 031 | F53: 03.1 | G53: 4 | H53: This class includes: - fishing on a commercial basis in inland waters - taking of freshwater crustaceans and molluscs - taking of freshwater aquatic animals This class also includes: - gathering of freshwater materials - gathering of other freshwater organisms: seaweed and algae This class excludes: - catching of frogs or collection of snails in the wild, see 01.70 - collecting wild plants (e.g. reeds, sedges), see 02.30 - processing of fish, crustaceans and molluscs on factory ships or in factories ashore, see 10.20 - fishing inspection, protection and patrol services, see 84.24 - fishing practiced for sport or recreation and related services, see 93.19 - operation of sport fishing preserves, see 93.19
A54: 032 | B54: =IF(G54>1,VLOOKUP(LEFT(C54,2),Sheet1!$A$2:$B$88,2,FALSE),C54) -> A | C54: 03.2 | D54: Aquaculture | E54: 03 | F54: 03 | G54: 3 | H54: This group includes aquaculture (or aquafarming), in other words, the production process involving the culturing or farming (including harvesting) of aquatic organisms (for example, fish, molluscs, crustaceans, plants, amphibians) using techniques designed to increase the production of the organisms in question beyond the natural capacity of the environment (for example, regular stocking, feeding and protection from predators). Aquaculture also encompasses individual, corporate or state ownership of the individual organisms throughout the rearing or culture stage, up to and including harvesting. Culturing/farming refers to the rearing up to their juvenile and/or adult phase under captive conditions of the above organisms. This group also includes: - breeding/farming of fry and adults under artificial conditions This group excludes: - production of bird skins from ranching operations or skins from farming reptiles (e.g. snakes and turtles), see 01.48 - breeding and raising of reptiles, see 01.48
A55: 0321 | B55: =IF(G55>1,VLOOKUP(LEFT(C55,2),Sheet1!$A$2:$B$88,2,FALSE),C55) -> A | C55: 03.21 | D55: Marine aquaculture | E55: 032 | F55: 03.2 | G55: 4 | H55: This class includes: - fish farming in sea water, including farming of marine ornamental fish - production of bivalve spat (e.g. oyster mussel, etc.), lobsterlings, shrimp post-larvae, fish fry and fingerlings - growing of seaweed and algae - culture of crustaceans, bivalves, other molluscs and other aquatic animals in sea water This class also includes: - aquaculture activities in brackish waters - land-based aquaculture activities in salt water filled tanks and reservoirs - operation of marine fish hatcheries and marine worm farms - marine microalgae cultivation This class excludes: - frog farming, see 03.22 - operation of sport fishing preserves, see 93.19
A56: 0322 | B56: =IF(G56>1,VLOOKUP(LEFT(C56,2),Sheet1!$A$2:$B$88,2,FALSE),C56) -> A | C56: 03.22 | D56: Freshwater aquaculture | E56: 032 | F56: 03.2 | G56: 4 | H56: This class includes: - fish farming in freshwater, including farming of freshwater ornamental fish - culture of freshwater crustaceans, bivalves, other molluscs and other aquatic animals - operation of fish hatcheries (freshwater) - farming of frogs - growing of seaweed and algae (edible or not) This class also includes: - freshwater microalgae cultivation This class excludes: - aquaculture activities in salt water filled tanks and reservoirs, see 03.21 - operation of sport fishing preserves, see 93.19
A57: 033 | B57: =IF(G57>1,VLOOKUP(LEFT(C57,2),Sheet1!$A$2:$B$88,2,FALSE),C57) -> A | C57: 03.3 | D57: Support activities for fishing and aquaculture | E57: 03 | F57: 03 | G57: 3
A58: 0330 | B58: =IF(G58>1,VLOOKUP(LEFT(C58,2),Sheet1!$A$2:$B$88,2,FALSE),C58) -> A | C58: 03.30 | D58: Support activities for fishing and aquaculture | E58: 033 | F58: 03.3 | G58: 4 | H58: This class includes: - service activities incidental to marine or freshwater fishery or aquaculture, e.g.: • diving services for aquaculture • remotely operated underwater vehicles (ROV) services for aquaculture • repair and maintenance services for fish cages • other support activities on fishing and aquaculture n.e.c. This class also includes: - fishery (fishery guard) and aquaculture control This class excludes: - fishing and aquaculture activities, see 03.1, 03.2 - processing of fish and aquaculture products on factory ships or in factories ashore, see 10.20 - processing of fish, crustaceans and molluscs, see 10.20 - activities related to the servicing of equipment and/or vessels, see division 33 - distribution of fisheries and aquaculture products, see divisions 46, 47, 52 - fishing practiced for sport or recreation and related services, see 93.19 - operation of sport fishing preserves, see 93.19
A59: B | B59: =IF(G59>1,VLOOKUP(LEFT(C59,2),Sheet1!$A$2:$B$88,2,FALSE),C59) -> B | C59: B | D59: MINING AND QUARRYING | G59: 1 | H59: Mining and quarrying include the extraction of minerals occurring naturally as solids (coal and ores), liquids (petroleum) or gases (natural gas). Extraction can be achieved by different methods (for example, underground or surface mining, well operation, seabed mining). This section includes supplementary activities aimed at preparing the crude materials for marketing (for example, crushing, grinding, cleaning, drying, sorting, concentrating ores and liquefaction of natural gas). Mining activities are classified into divisions, groups and classes on the basis of the principal mineral produced. Divisions 05 and 06 are concerned with mining and quarrying of fossil fuels (coal, lignite, petroleum, gas); divisions 07 and 08 concern metal ores, various minerals and quarry products. Some of the technical operations of this section, particularly related to the extraction of hydrocarbons, may also be carried out for third parties by specialised units as an industrial service activity which is reflected in division 09. This section excludes: - further processing of the extracted materials, see section C - use of the extracted materials without further transformation for construction purposes, see section F - bottling of natural spring and mineral waters at springs and wells, see 11.07 - remediation of mine sites, see 39.00
A60: 05 | B60: =IF(G60>1,VLOOKUP(LEFT(C60,2),Sheet1!$A$2:$B$88,2,FALSE),C60) -> B | C60: 05 | D60: Mining of coal and lignite | E60: B | F60: B | G60: 2 | H60: This division includes the extraction of solid mineral fuels through underground or open-cast mining and includes operations (for example, grading, cleaning, compressing and other steps necessary for transport) leading to a marketable product. This division excludes: - coking, see 19.10 - services incidental to coal or lignite mining, see 09.90 - manufacture of briquettes, see 19.20
A61: 051 | B61: =IF(G61>1,VLOOKUP(LEFT(C61,2),Sheet1!$A$2:$B$88,2,FALSE),C61) -> B | C61: 05.1 | D61: Mining of hard coal | E61: 05 | F61: 05 | G61: 3
A62: 0510 | B62: =IF(G62>1,VLOOKUP(LEFT(C62,2),Sheet1!$A$2:$B$88,2,FALSE),C62) -> B | C62: 05.10 | D62: Mining of hard coal | E62: 051 | F62: 05.1 | G62: 4 | H62: This class includes: - mining of hard coal: underground or surface mining, including mining through liquefaction methods - cleaning, sizing, grading, pulverising, compressing, etc. of coal to classify, improve quality or facilitate transport or storage This class also includes: - recovery of hard coal from culm banks This class excludes: - lignite mining, see 05.20 - peat digging, see 08.92 - support activities for hard coal mining, see 09.90 - test drilling for coal mining, see 09.90 - coke ovens producing solid fuels, see 19.10 - manufacture of hard coal briquettes, ovoids and similar solid hard coal fuels, see 19.20 - work performed to develop or prepare properties for coal mining, see 43.12
A63: 052 | B63: =IF(G63>1,VLOOKUP(LEFT(C63,2),Sheet1!$A$2:$B$88,2,FALSE),C63) -> B | C63: 05.2 | D63: Mining of lignite | E63: 05 | F63: 05 | G63: 3
A64: 0520 | B64: =IF(G64>1,VLOOKUP(LEFT(C64,2),Sheet1!$A$2:$B$88,2,FALSE),C64) -> B | C64: 05.20 | D64: Mining of lignite | E64: 052 | F64: 05.2 | G64: 4 | H64: This class includes: - mining of lignite (brown coal): underground or surface mining, including mining through liquefaction methods - washing, dehydrating, pulverising, compressing of lignite to improve quality or facilitate transport or storage This class excludes: - hard coal mining, see 05.10 - peat digging, see 08.92 - support activities for lignite mining, see 09.90 - test drilling for coal mining, see 09.90 - manufacture of lignite fuel briquettes, ovoids and similar solid lignite fuels, see 19.20 - work performed to develop or prepare properties for lignite mining, see 43.12
A65: 06 | B65: =IF(G65>1,VLOOKUP(LEFT(C65,2),Sheet1!$A$2:$B$88,2,FALSE),C65) -> B | C65: 06 | D65: Extraction of crude petroleum and natural gas | E65: B | F65: B | G65: 2 | H65: This division includes the production of crude petroleum, the mining and extraction of oil from oil shale and oil sands, and the production of natural gas and recovery of hydrocarbon liquids. This division also includes the activities of operating and/or developing oilfields and gas fields. Such activities may include drilling, completing and equipping wells; operating separators, emulsion breakers, desalting equipment and field-gathering lines for crude petroleum; all other activities in the preparation of oil and gas up to the point of shipment from the producing property. This division excludes: - support activities for oilfields and gas fields, performed on a fee or contract basis, see 09.10 - exploration of oil and gas wells, see 09.10 - test drilling and boring in connection with petroleum or gas extraction, see 09.10 - refining of petroleum products, see 19.20 - geophysical, geologic and seismic surveying, see 71.12
A66: 061 | B66: =IF(G66>1,VLOOKUP(LEFT(C66,2),Sheet1!$A$2:$B$88,2,FALSE),C66) -> B | C66: 06.1 | D66: Extraction of crude petroleum | E66: 06 | F66: 06 | G66: 3
A67: 0610 | B67: =IF(G67>1,VLOOKUP(LEFT(C67,2),Sheet1!$A$2:$B$88,2,FALSE),C67) -> B | C67: 06.10 | D67: Extraction of crude petroleum | E67: 061 | F67: 06.1 | G67: 4 | H67: This class includes: - extraction of crude petroleum oils This class also includes: - extraction of bituminous or oil shale and tar sand - production of crude petroleum from bituminous shale and sand - processes to obtain crude oils (e.g. decantation, desalting, dehydration, stabilisation) This class excludes: - extraction of condensates or natural gas liquids, see 06.20 - support activities for oil and natural gas extraction, see 09.10 - oil and gas exploration, see 09.10 - production of natural gas liquids from crude petroleum (crude oil), see 19.20 - manufacture of refined petroleum products, see 19.20 - recovery of liquefied petroleum gases in the refining of petroleum, see 19.20 - operation of pipelines, see 49.50
A68: 062 | B68: =IF(G68>1,VLOOKUP(LEFT(C68,2),Sheet1!$A$2:$B$88,2,FALSE),C68) -> B | C68: 06.2 | D68: Extraction of natural gas | E68: 06 | F68: 06 | G68: 3
A69: 0620 | B69: =IF(G69>1,VLOOKUP(LEFT(C69,2),Sheet1!$A$2:$B$88,2,FALSE),C69) -> B | C69: 06.20 | D69: Extraction of natural gas | E69: 062 | F69: 06.2 | G69: 4 | H69: This class includes: - production of crude gaseous hydrocarbon (natural gas) - extraction of condensates - draining and separation of liquid hydrocarbon fractions - gas desulphurisation - extraction of coal mine methane This class also includes: - mining of hydrocarbon liquids obtained through liquefaction or pyrolysis - fracking to extract coal seam gas This class excludes: - support activities for oil and natural gas extraction, see 09.10 - oil and gas exploration, see 09.10 - production of natural gas liquids from crude petroleum (crude oil), see 19.20 - recovery of liquefied petroleum gases in the refining of petroleum, see 19.20 - manufacture of industrial gases, see 20.11 - operation of pipelines, see 49.50
A70: 07 | B70: =IF(G70>1,VLOOKUP(LEFT(C70,2),Sheet1!$A$2:$B$88,2,FALSE),C70) -> B | C70: 07 | D70: Mining of metal ores | E70: B | F70: B | G70: 2 | H70: This division includes mining for metallic minerals (ores), performed through underground or open-cast extraction, seabed mining, and so on. This division also includes: - ore dressing and beneficiating operations (e.g. crushing, grinding, washing, drying, sintering, calcining or leaching ore, gravity separation or flotation operations) This division excludes: - roasting of iron pyrites, see 20.13 - operation of blast furnaces, see division 24 - production of aluminium oxide, see 24.42
A71: 071 | B71: =IF(G71>1,VLOOKUP(LEFT(C71,2),Sheet1!$A$2:$B$88,2,FALSE),C71) -> B | C71: 07.1 | D71: Mining of iron ores | E71: 07 | F71: 07 | G71: 3
A72: 0710 | B72: =IF(G72>1,VLOOKUP(LEFT(C72,2),Sheet1!$A$2:$B$88,2,FALSE),C72) -> B | C72: 07.10 | D72: Mining of iron ores | E72: 071 | F72: 07.1 | G72: 4 | H72: This class includes: - mining of ores valued chiefly for iron content - beneficiation of iron ores This class excludes: - extraction and preparation of pyrites and pyrrhotite (except roasting), see 08.91
A73: 072 | B73: =IF(G73>1,VLOOKUP(LEFT(C73,2),Sheet1!$A$2:$B$88,2,FALSE),C73) -> B | C73: 07.2 | D73: Mining of non-ferrous metal ores | E73: 07 | F73: 07 | G73: 3 | H73: This group includes the mining of non-ferrous metal ores.
A74: 0721 | B74: =IF(G74>1,VLOOKUP(LEFT(C74,2),Sheet1!$A$2:$B$88,2,FALSE),C74) -> B | C74: 07.21 | D74: Mining of uranium and thorium ores | E74: 072 | F74: 07.2 | G74: 4 | H74: This class includes: - mining of ores chiefly valued for uranium and thorium content: pitchblende, etc. - concentration of such ores - manufacture of yellowcake This class excludes: - enrichment of uranium and thorium ores, see 20.13 - production of uranium metal from pitchblende or other ores, see 24.46 - smelting and refining of uranium, see 24.46
A75: 0729 | B75: =IF(G75>1,VLOOKUP(LEFT(C75,2),Sheet1!$A$2:$B$88,2,FALSE),C75) -> B | C75: 07.29 | D75: Mining of other non-ferrous metal ores | E75: 072 | F75: 07.2 | G75: 4 | H75: This class includes: - mining and preparation of ores chiefly valued for non-ferrous metal content: • aluminium (bauxite), copper, lead, zinc, tin, manganese, chrome, nickel, cobalt, molybdenum, tantalum, vanadium, lithium/spodumene, etc. • precious metals: gold, silver, platinum This class excludes: - mining and preparation of uranium and thorium ores, see 07.21 - production of aluminium oxide, see 24.42 - production of mattes of copper, see 24.44 - production of mattes of nickel, see 24.45
A76: 08 | B76: =IF(G76>1,VLOOKUP(LEFT(C76,2),Sheet1!$A$2:$B$88,2,FALSE),C76) -> B | C76: 08 | D76: Other mining and quarrying | E76: B | F76: B | G76: 2 | H76: This division includes extraction from a mine or quarry, but also dredging of alluvial deposits, rock crushing and the use of salt marshes. The products are used most notably in construction (for example, sands, stones), the manufacture of materials (for example, clay, gypsum, calcium), the manufacture of chemicals, and so on. This division excludes processing (except crushing, grinding, cutting, cleaning, drying, sorting and mixing) of the minerals extracted, see section C.
A77: 081 | B77: =IF(G77>1,VLOOKUP(LEFT(C77,2),Sheet1!$A$2:$B$88,2,FALSE),C77) -> B | C77: 08.1 | D77: Quarrying of stone, sand and clay | E77: 08 | F77: 08 | G77: 3
A78: 0811 | B78: =IF(G78>1,VLOOKUP(LEFT(C78,2),Sheet1!$A$2:$B$88,2,FALSE),C78) -> B | C78: 08.11 | D78: Quarrying of ornamental stone, limestone, gypsum, slate and other stone | E78: 081 | F78: 08.1 | G78: 4 | H78: This class includes: - quarrying, rough trimming and sawing of monumental and building stone (for example, marble, granite, sandstone) - breaking and crushing of ornamental and building stone - quarrying, crushing and breaking of limestone - mining of gypsum and anhydrite - mining of chalk and uncalcined dolomite - production of granules, chippings and powder of extracted stones, whether heat-treated or not This class excludes: - mining of chemical and fertiliser minerals, see 08.91 - production of calcined dolomite, see 23.52 - cutting, shaping and finishing of stone outside quarries, see 23.70
A79: 0812 | B79: =IF(G79>1,VLOOKUP(LEFT(C79,2),Sheet1!$A$2:$B$88,2,FALSE),C79) -> B | C79: 08.12 | D79: Operation of gravel and sand pits and mining of clay and kaolin | E79: 081 | F79: 08.1 | G79: 4 | H79: This class includes: - extraction and dredging of industrial sand, sand for construction and gravel - breaking and crushing of gravel - quarrying of sand - mining of clays, refractory clays and kaolin This class excludes: - mining of bituminous sand, see 06.10
A80: 089 | B80: =IF(G80>1,VLOOKUP(LEFT(C80,2),Sheet1!$A$2:$B$88,2,FALSE),C80) -> B | C80: 08.9 | D80: Mining and quarrying n.e.c. | E80: 08 | F80: 08 | G80: 3
A81: 0891 | B81: =IF(G81>1,VLOOKUP(LEFT(C81,2),Sheet1!$A$2:$B$88,2,FALSE),C81) -> B | C81: 08.91 | D81: Mining of chemical and fertiliser minerals | E81: 089 | F81: 08.9 | G81: 4 | H81: This class includes: - mining of natural phosphates and natural potassium salts - mining of native sulphur - extraction and preparation of pyrites and pyrrhotite, except roasting - mining of natural barium sulphate and carbonate (barytes and witherite), natural borates, natural magnesium sulphates (kieserite) - mining of earth colours, fluorspar and other minerals valued chiefly as a source of chemicals This class also includes: - guano mining - mining of medicinal mud - extraction processes to produce lithium from brine This class excludes: - extraction of salt, see 08.93 - roasting of iron pyrites, see 20.13 - manufacture of synthetic fertilisers and nitrogen compounds, see 20.15
A82: 0892 | B82: =IF(G82>1,VLOOKUP(LEFT(C82,2),Sheet1!$A$2:$B$88,2,FALSE),C82) -> B | C82: 08.92 | D82: Extraction of peat | E82: 089 | F82: 08.9 | G82: 4 | H82: This class includes: - peat digging - preparation of peat to improve quality or facilitate transport/storage This class excludes: - service activities incidental to peat mining, see 09.90 - manufacture of peat briquettes, see 19.20 - manufacture of potting soil mixtures (e.g. of peat, natural soil, sands, clays, fertiliser minerals), see 20.15 - manufacture of articles of peat, see 23.99
A83: 0893 | B83: =IF(G83>1,VLOOKUP(LEFT(C83,2),Sheet1!$A$2:$B$88,2,FALSE),C83) -> B | C83: 08.93 | D83: Extraction of salt | E83: 089 | F83: 08.9 | G83: 4 | H83: This class includes: - extraction of salt from underground, including by dissolving and pumping - salt production by evaporation of sea water or other saline waters - crushing, purification and refining of salt by the producer This class excludes: - processing of salt into food-grade salt (e.g. iodised salt), see 10.84 - potable water production by evaporation of saline water, see 36.00
A84: 0899 | B84: =IF(G84>1,VLOOKUP(LEFT(C84,2),Sheet1!$A$2:$B$88,2,FALSE),C84) -> B | C84: 08.99 | D84: Other mining and quarrying n.e.c. | E84: 089 | F84: 08.9 | G84: 4 | H84: This class includes: - mining and quarrying of various minerals and materials: • abrasive materials, asbestos, siliceous fossil meals, natural graphite, steatite (talc), feldspar, etc. • natural asphalt, asphaltites and asphaltic rock; natural solid bitumen • gemstones, quartz, mica, etc.
A85: 09 | B85: =IF(G85>1,VLOOKUP(LEFT(C85,2),Sheet1!$A$2:$B$88,2,FALSE),C85) -> B | C85: 09 | D85: Mining support service activities | E85: B | F85: B | G85: 2 | H85: This division includes specialised support services incidental to mining provided on a fee or contract basis. It includes exploration services through traditional prospecting methods (for example, taking core samples and making geological observations as well as drilling, test drilling or redrilling for oil wells, metallic and non-metallic minerals). Other typical services cover building oil and gas well foundations, cementing oil and gas well casings, cleaning, bailing and swabbing oil and gas wells, draining and pumping mines, and so on.
A86: 091 | B86: =IF(G86>1,VLOOKUP(LEFT(C86,2),Sheet1!$A$2:$B$88,2,FALSE),C86) -> B | C86: 09.1 | D86: Support activities for petroleum and natural gas extraction | E86: 09 | F86: 09 | G86: 3
A87: 0910 | B87: =IF(G87>1,VLOOKUP(LEFT(C87,2),Sheet1!$A$2:$B$88,2,FALSE),C87) -> B | C87: 09.10 | D87: Support activities for petroleum and natural gas extraction | E87: 091 | F87: 09.1 | G87: 4 | H87: This class includes: - oil and gas extraction service activities provided on a fee or contract basis: • exploration services in connection with petroleum or gas extraction (e.g. traditional prospecting methods, making geological observations at prospective sites) • directional drilling and redrilling; 'spudding in'; derrick erection in situ, repairing and dismantling; cementing oil and gas well casings; pumping of wells; plugging and abandoning wells, etc. • liquefaction and regasification of natural gas for the purpose of transport, done at the mine site • draining and pumping services on a fee or contract basis • test drilling in connection with petroleum or gas extraction This class also includes: - firefighting services and fire-prevention services for oilfields and gas fields This class excludes: - service activities performed by operators of oilfields or gas fields, see 06.10, 06.20 - specialised repair and maintenance of drilling and extraction machinery and equipment, see 33.12 - specialised offshore installation, repair and maintenance of equipment that forms an integral part of floating platforms, see division 43 - liquefaction and regasification of natural gas for the purpose of land or water transport, not done at the mine site, see 52.21 or 52.22 - geophysical surveying services, on a contract or fee basis, see 71.12
A88: 099 | B88: =IF(G88>1,VLOOKUP(LEFT(C88,2),Sheet1!$A$2:$B$88,2,FALSE),C88) -> B | C88: 09.9 | D88: Support activities for other mining and quarrying | E88: 09 | F88: 09 | G88: 3
A89: 0990 | B89: =IF(G89>1,VLOOKUP(LEFT(C89,2),Sheet1!$A$2:$B$88,2,FALSE),C89) -> B | C89: 09.90 | D89: Support activities for other mining and quarrying | E89: 099 | F89: 09.9 | G89: 4 | H89: This class includes: - support services on a fee or contract basis, required for mining activities of divisions 05, 07, 08 • exploration services by using traditional prospecting methods (e.g. taking core samples and making geological observations at prospective sites) • draining and pumping services on a fee or contract basis • test drilling and test hole boring - securing mine shafts and tunnels - demolition and dismantling of underground mining facilities This class excludes: - operating mines or quarries on a contract or fee basis, see divisions 05, 07, 08 - specialised repair and maintenance of mining machinery, see 33.12 - geophysical surveying services, on a contract or fee basis, see 71.12
A90: C | B90: =IF(G90>1,VLOOKUP(LEFT(C90,2),Sheet1!$A$2:$B$88,2,FALSE),C90) -> C | C90: C | D90: MANUFACTURING | G90: 1 | H90: This section includes the physical, mechanical, chemical or biological transformation of materials, substances, or components into new products, although this cannot be used as the single universal criterion for defining manufacturing (see remark on processing of waste below). The materials, substances, or components undergoing transformation are either raw materials or products of agriculture, forestry, fishing, mining or quarrying as well as products of other manufacturing activities. Substantial alteration, renovation or reconstruction of goods is generally considered to be manufacturing. The output of a manufacturing process may be finished in the sense that it is ready for use or consumption, or it may be semi-finished in the sense that it is to become an input for further manufacturing. For example, the output of alumina refining is the input used in the primary production of aluminium; primary aluminium is the input to aluminium wire drawing; aluminium wire is the input for the manufacture of fabricated wire products. Manufacture of specialised components and parts of, and accessories and attachments to machinery and equipment is, as a general rule, classified in the same class as the manufacture of the machinery and equipment for which the parts and accessories are intended. Manufacture of unspecialised components and parts of machinery and equipment (for example, engines, pistons, electric motors, electrical assemblies, valves, gears, roller bearings, is classified in the appropriate class of manufacturing, without regard to the machinery and equipment in which these items may be included. Making specialised components and accessories by moulding or extruding plastics materials is usually included in group 22.2. Assembly of the component parts of manufactured products is considered manufacturing. This includes the assembly of manufactured products from either self-produced or purchased components. The recovery of waste, in other words, the processing of waste into secondary raw materials* is classified in group 38.2. While this may involve physical, mechanical, biological or chemical transformations, this is not considered to be a part of manufacturing activities. The primary purpose of these activities is considered to be the treatment or processing of waste and they are therefore classified in section E. However, the manufacture of new products from secondary raw materials is classified in manufacturing, even if these processes use waste as an input (for example, the production of silver from film waste is considered to be a manufacturing process). Specialised maintenance and repair of industrial, commercial and similar machinery and equipment is, in general, classified in division 33. However, the repair and maintenance of computers, personal and household goods, motor vehicles and motorcycles is classified in division 95. The installation of machinery and equipment, when carried out as a specialised activity, is classified in class 33.20. Maintenance, repair and installation of equipment that forms an integral part of buildings or similar structures (for example, maintenance, repair and installation of escalators or of air-conditioning systems, is classified as construction in section F, if carried out at the construction site). This section also contains the activities of factoryless goods producers (FGPs) in manufacturing (see introductory guidelines, paragraph xx). As a general rule, the activities in the manufacturing section involve the transformation of materials into new, rebuilt and remanufactured products. Their output is a new product. As clarification, the following activities are considered manufacturing in NACE: - fresh fish processing (oyster shucking, fish filleting), not done on a fishing boat, see 10.20 - milk pasteurising and bottling, see 10.51 - leather converting, see 15.11 - wood preserving, see 16.12 - printing and related activities, excluding published goods, see 18.1 - tyre retreading, see 22.11 - ready-mixed concrete production, see 23.63 - galvanising, electroplating, plating, etc., and other metallic or non-metallic coating of metals, see 25.51 - heat treatment of metals, see 25.52 - refilling of ink cartridges, see 26.20 - refilling or recharging of fire extinguishers, see 28.29 - rebuilding or remanufacture of machinery (e.g. automobile engines), see 29.10 - assembly provided by a seller or blending of several products to be sold. If assembly is provided by a contractor, this activity should be classified in manufacturing. Conversely, there are activities that, although sometimes involving transformation processes, are classified in other sections of NACE; in other words, they are not considered as manufacturing. They include: - logging, classified in section A - beneficiating of agricultural products, classified in section A - preparation of food for immediate consumption on the premises, classified in division 56 - beneficiating of ores and other minerals, classified in section B - production of gaseous fuels for energy supply through a permanent network, classified in section D - production of compost from organic waste, classified in section E - assembly provided as part of a delivery or by a seller; however, if assembly is the main activity provided by a contractor, it is classified in manufacturing - activities of breaking bulk and redistribution in smaller lots, including packaging, repackaging, or bottling products (e.g. as liquors or chemicals); sorting and reselling of scrap; mixing paints to customer order; cutting metals to customer order; treatment not resulting in a different good, classified in section G - publishing and the combined activities of publishing and printing, classified in section J Note: * secondary raw materials are materials and products which can be used as raw materials by simple reuse, or via recycling and recovery.
A91: 10 | B91: =IF(G91>1,VLOOKUP(LEFT(C91,2),Sheet1!$A$2:$B$88,2,FALSE),C91) -> C | C91: 10 | D91: Manufacture of food products | E91: C | F91: C | G91: 2 | H91: This division includes the processing of products of agriculture, forestry and fishing into food for humans or animals, and includes the production of various intermediate products that are not directly food products. The activity often generates associated products of greater or lesser value (for example, hides from slaughtering, or oilcake from oil production). This division is organised by activities dealing with different kinds of products: meat, fish, fruits and vegetables, fats and oils, milk products, grain mill products, animal feed and other food products. Production can be carried out for own account, as well as for third parties, as in custom slaughtering. Some activities are considered manufacturing even though there is retail sale of the products in the producers’ own shop (for example, those activities performed in bakeries, pastry shops and prepared meat shops which sell their own production). However, where the processing is minimal and does not lead to a real transformation, the unit is classified to section G. This division also includes the manufacture of liquids considered food or that use similar manufacturing processes (for example, milk and fruit juice/ concentrate). This division excludes the preparation of meals for immediate consumption, see division 56.
A92: 101 | B92: =IF(G92>1,VLOOKUP(LEFT(C92,2),Sheet1!$A$2:$B$88,2,FALSE),C92) -> C | C92: 10.1 | D92: Processing and preserving of meat and production of meat products | E92: 10 | F92: 10 | G92: 3
A93: 1011 | B93: =IF(G93>1,VLOOKUP(LEFT(C93,2),Sheet1!$A$2:$B$88,2,FALSE),C93) -> C | C93: 10.11 | D93: Processing and preserving of meat, except of poultry meat | E93: 101 | F93: 10.1 | G93: 4 | H93: This class includes: - operation of slaughterhouses engaged in killing, dressing or packing meat: beef, pork, lamb, rabbit, mutton, camel, etc. - production of fresh, chilled or frozen meat, in carcasses - production of fresh, chilled or frozen meat, in cuts This class also includes: - slaughtering and processing of whales on land or on specialised vessels - production of hides and skins originating from slaughterhouses (e.g. by fellmongery and salting) - rendering and refining of lard and other edible animal fats - processing of animal offal - production of pulled wool This class excludes: - rendering of edible poultry fats, see 10.12 - production of dried, salted or smoked meat, and meat products, see 10.13
A94: 1012 | B94: =IF(G94>1,VLOOKUP(LEFT(C94,2),Sheet1!$A$2:$B$88,2,FALSE),C94) -> C | C94: 10.12 | D94: Processing and preserving of poultry meat | E94: 101 | F94: 10.1 | G94: 4 | H94: This class includes: - operation of slaughterhouses engaged in killing, dressing or packing poultry - production of fresh, chilled or frozen meat in individual portions - rendering of edible poultry fats This class also includes: - cleaning, disinfecting, treating for preservation, and trimming of feathers and down
A95: 1013 | B95: =IF(G95>1,VLOOKUP(LEFT(C95,2),Sheet1!$A$2:$B$88,2,FALSE),C95) -> C | C95: 10.13 | D95: Production of meat and poultry meat products | E95: 101 | F95: 10.1 | G95: 4 | H95: This class includes: - production of preserved meat (e.g. by cooking, drying, salting or smoking) - production of meat products: • sausages, salami, puddings, andouillettes, saveloys, bolognas, pâtés, rillettes, boiled ham This class excludes: - manufacture of prepared meat and poultry dishes, see 10.85 - manufacture of soup containing meat, see 10.89 - wholesale of meat, see 46.32
A96: 102 | B96: =IF(G96>1,VLOOKUP(LEFT(C96,2),Sheet1!$A$2:$B$88,2,FALSE),C96) -> C | C96: 10.2 | D96: Processing and preserving of fish, crustaceans and molluscs | E96: 10 | F96: 10 | G96: 3
A97: 1020 | B97: =IF(G97>1,VLOOKUP(LEFT(C97,2),Sheet1!$A$2:$B$88,2,FALSE),C97) -> C | C97: 10.20 | D97: Processing and preserving of fish, crustaceans and molluscs | E97: 102 | F97: 10.2 | G97: 4 | H97: This class includes: - preparation and preservation of fish, crustaceans and molluscs (e.g. freezing, deep-freezing, drying, cooking, smoking, salting, immersing in brine, canning) - production of fish, crustacean and mollusc products: fish fillets, roes, caviar, caviar substitutes, etc. - production of fishmeal for human consumption or animal feed - production of meals and solubles from fish and other aquatic animals unfit for human consumption This class also includes: - activities of factory vessels not engaged in fishing and only in the processing and preserving of fish - processing of seaweed - removing fish heads, gutting and cutting fish into pieces, and then freezing This class excludes: - processing and preserving of fish on vessels engaged in fishing, see 03.11 - processing of whales on land or specialised vessels, see 10.11 - production of oils and fats of fish and marine mammals, see 10.41 - manufacture of prepared fish dishes, see 10.85 - manufacture of fish soups, see 10.89
A98: 103 | B98: =IF(G98>1,VLOOKUP(LEFT(C98,2),Sheet1!$A$2:$B$88,2,FALSE),C98) -> C | C98: 10.3 | D98: Processing and preserving of fruit and vegetables | E98: 10 | F98: 10 | G98: 3
A99: 1031 | B99: =IF(G99>1,VLOOKUP(LEFT(C99,2),Sheet1!$A$2:$B$88,2,FALSE),C99) -> C | C99: 10.31 | D99: Processing and preserving of potatoes | E99: 103 | F99: 10.3 | G99: 4 | H99: This class includes: - processing and preserving of potatoes: • manufacture of prepared frozen potatoes • manufacture of dehydrated mashed potatoes • manufacture of potato snacks • manufacture of potato crisps • manufacture of potato flour and meal • peeling and cutting of potatoes
A100: 1032 | B100: =IF(G100>1,VLOOKUP(LEFT(C100,2),Sheet1!$A$2:$B$88,2,FALSE),C100) -> C | C100: 10.32 | D100: Manufacture of fruit and vegetable juice | E100: 103 | F100: 10.3 | G100: 4 | H100: This class includes: - manufacture of fruit or vegetable juices This class also includes: - production of concentrates from fresh fruits and vegetables This class excludes: - manufacture of beverages produced with fruit nectars, see 11.07
A101: 1039 | B101: =IF(G101>1,VLOOKUP(LEFT(C101,2),Sheet1!$A$2:$B$88,2,FALSE),C101) -> C | C101: 10.39 | D101: Other processing and preserving of fruit and vegetables | E101: 103 | F101: 10.3 | G101: 4 | H101: This class includes: - manufacture of food consisting chiefly of fruits or vegetables - preserving of fruits, nuts or vegetables (e.g. freezing, drying, freeze-drying, drying by infra-red radiation, immersing in oil or in vinegar, canning, high pressure, high temperature) - manufacture of fruit or vegetable food products - manufacture of jams, marmalades and table jellies - shelling, peeling and roasting of nuts - manufacture of nut foods and pastes This class also includes: - manufacture of perishable prepared foods of fruits and vegetables, e.g.: • salads; mixed salads, packaged • peeled or cut vegetables • tofu (bean curd) This class excludes: - manufacture of fruit and vegetable juices, see 10.32 - manufacture of flour or meal of dried leguminous vegetables, see 10.61 - preservation of fruits and nuts in sugar, see 10.82 - manufacture of prepared vegetable dishes, see 10.85 - manufacture of artificial concentrates, see 10.89
A102: 104 | B102: =IF(G102>1,VLOOKUP(LEFT(C102,2),Sheet1!$A$2:$B$88,2,FALSE),C102) -> C | C102: 10.4 | D102: Manufacture of vegetable and animal oils and fats | E102: 10 | F102: 10 | G102: 3 | H102: This group includes the manufacture of crude and refined oils and fats from vegetable or animal materials. This group excludes the rendering or refining of lard and edible animal fats of bovine animals, sheep, goats, pigs and poultry, see 10.1.
A103: 1041 | B103: =IF(G103>1,VLOOKUP(LEFT(C103,2),Sheet1!$A$2:$B$88,2,FALSE),C103) -> C | C103: 10.41 | D103: Manufacture of oils and fats | E103: 104 | F103: 10.4 | G103: 4 | H103: This class includes: - manufacture of crude and refined vegetable oils (e.g. olive oil, soya-bean oil, hemp oil, sunflower seed oil, rape oil) - manufacture of non-defatted flour or meal of oilseeds, oil nuts or oil kernels - processing of vegetable oils (e.g. blowing, boiling, dehydration, hydrogenation) This class also includes: - manufacture of non-edible animal oils and fats - extraction of fish and marine mammal oils - production of cotton linters, oilcakes and other residual products of oil production This class excludes: - rendering and refining of lard and other edible fats of bovine animals, sheep, goats or pigs, see 10.11 - rendering of edible poultry fats, see 10.12 - manufacture of margarine, see 10.42 - wet corn milling, see 10.62 - manufacture of corn oil, see 10.62 - manufacture of essential oils, see 20.59 - treatment of oil and fats by chemical processes, see 20.59
A104: 1042 | B104: =IF(G104>1,VLOOKUP(LEFT(C104,2),Sheet1!$A$2:$B$88,2,FALSE),C104) -> C | C104: 10.42 | D104: Manufacture of margarine and similar edible fats | E104: 104 | F104: 10.4 | G104: 4 | H104: This class includes: - manufacture of margarine - manufacture of melanges and similar spreads - manufacture of compound cooking fats
A105: 105 | B105: =IF(G105>1,VLOOKUP(LEFT(C105,2),Sheet1!$A$2:$B$88,2,FALSE),C105) -> C | C105: 10.5 | D105: Manufacture of dairy products and edible ice | E105: 10 | F105: 10 | G105: 3 | H105: This group excludes: - production of plant-based milk substitutes, see 11.07
A106: 1051 | B106: =IF(G106>1,VLOOKUP(LEFT(C106,2),Sheet1!$A$2:$B$88,2,FALSE),C106) -> C | C106: 10.51 | D106: Manufacture of dairy products | E106: 105 | F106: 10.5 | G106: 4 | H106: This class includes: - manufacture of fresh liquid milk, pasteurised, sterilised, homogenised and/or ultra-heat treated - manufacture of milk-based drinks - manufacture of cream from fresh liquid milk, pasteurised, sterilised, homogenised - manufacture of dried or concentrated milk, whether or not sweetened - manufacture of milk or cream in solid form - manufacture of butter - manufacture of yoghurt - manufacture of cheese and curd - refining and ageing cheese - manufacture of whey - manufacture of casein - manufacture of lactose-free dairy products This class also includes: - manufacture of milk kefir - manufacture of lactose and lactose syrup This class excludes: - production of raw milk of cattle, see 01.41 - production of raw milk of sheep, goats, horses, asses, camels, etc., see 01.43, 01.44, 01.45 - production of milk-based dietary drinks, see 10.86 - production of dairy-based infant formulae, see 10.86 - manufacture of cheese substitutes, see 10.89 - manufacture of fruit kefir and water kefir, see 11.03 - manufacture of non-dairy milk (e.g. plant-based milk), see 11.07
...

Sheet Sheet1
A1: CODE | B1: PARENT_CODE | C1: LEVEL
A2: 01 | B2: A | C2: 2
A3: 02 | B3: A | C3: 2
A4: 03 | B4: A | C4: 2
A5: 05 | B5: B | C5: 2
A6: 06 | B6: B | C6: 2
A7: 07 | B7: B | C7: 2
A8: 08 | B8: B | C8: 2
A9: 09 | B9: B | C9: 2
A10: 10 | B10: C | C10: 2
A11: 11 | B11: C | C11: 2
A12: 12 | B12: C | C12: 2
... A88: 99 | B88: V | C88: 2
